djxero/__init__.py
djxero/admin.py
djxero/apps.py
djxero/decorators.py
djxero/middleware.py
djxero/models.py
djxero/tests.py
djxero/urls.py
djxero/views.py
djxero/templates/xero/interstitial.html
django_xero-0.0.3.dist-info/LICENSE
django_xero-0.0.3.dist-info/METADATA
django_xero-0.0.3.dist-info/NOTICE
django_xero-0.0.3.dist-info/WHEEL
django_xero-0.0.3.dist-info/top_level.txt
django_xero-0.0.3.dist-info/RECORD
