Metadata-Version: 2.1
Name: django-xero
Version: 0.0.3
Summary: Xero integration for Django
Home-page: https://github.com/toyg/django-xero
Author: Giacomo Lacava
Author-email: giac@autoepm.com
License: Apache Software License v.2
Platform: UNKNOWN
Classifier: Environment :: Web Environment
Classifier: Framework :: Django
Classifier: Framework :: Django :: 2.0
Classifier: Framework :: Django :: 2.1
Classifier: Framework :: Django :: 2.2
Classifier: Intended Audience :: Developers
Classifier: Intended Audience :: Financial and Insurance Industry
Classifier: License :: OSI Approved :: Apache Software License
Classifier: Development Status :: 4 - Beta
Classifier: Operating System :: OS Independent
Classifier: Programming Language :: Python
Classifier: Programming Language :: Python :: 3 :: Only
Classifier: Programming Language :: Python :: 3.7
Classifier: Programming Language :: Python :: 3.6
Classifier: Topic :: Internet :: WWW/HTTP
Classifier: Topic :: Internet :: WWW/HTTP :: Dynamic Content
Classifier: Topic :: Internet :: WWW/HTTP :: Session
Classifier: Topic :: Office/Business :: Financial
Classifier: Topic :: Office/Business :: Financial :: Accounting
Requires-Dist: Django (<3.0,>=2.2.3)
Requires-Dist: cryptography (<3.0,>=2.7)
Requires-Dist: django-encrypted-model-fields (<0.6,>=0.5.8)
Requires-Dist: pyxero (<1.0,>=0.9.1)
